{
  "elements": [
    {
      "id": "ec8de063-2949-4f20-b8ac-12b41ebf0bb2",
      "type": "rectangle",
      "x": 477.77777099609375,
      "y": 111.11112976074219,
      "width": 153.3333740234375,
      "height": 119.99998474121094,
      "strokeColor": "#000000",
      "backgroundColor": "transparent",
      "fillStyle": "conic",
      "strokeWidth": 2,
      "strokeStyle": "solid",
      "roughness": 1,
      "opacity": 100,
      "angle": 0,
      "renderStyle": "sketch",
      "seed": 263959696,
      "roundness": null,
      "locked": false,
      "link": null,
      "layerId": "default-layer",
      "startArrowhead": null,
      "endArrowhead": null,
      "fontSize": 20,
      "fontFamily": "hand-drawn",
      "textAlign": "left",
      "curveType": "straight",
      "gradientStops": [
        {
          "offset": 0,
          "color": "#ea0606"
        },
        {
          "offset": 0.5,
          "color": "#a01313"
        },
        {
          "offset": 0.5,
          "color": "#888888"
        },
        {
          "offset": 1,
          "color": "#9f0404"
        }
      ]
    }
  ],
  "viewState": {
    "scale": 1,
    "panX": 0,
    "panY": 133.33333686546058
  },
  "layers": [
    {
      "id": "default-layer",
      "name": "Layer 1",
      "visible": true,
      "locked": false,
      "opacity": 1,
      "order": 0,
      "backgroundColor": "transparent",
      "isGroup": false,
      "expanded": true
    }
  ],
  "gridSettings": {
    "enabled": false,
    "snapToGrid": false,
    "objectSnapping": true,
    "gridSize": 20,
    "gridColor": "#cccccc",
    "gridOpacity": 0.5,
    "style": "lines"
  },
  "canvasBackgroundColor": "#ffffff",
  "version": 2
}